{
    "compatibilities": [
        "EC2"
    ],
    "containerDefinitions": [
        {
            "cpu": 922,
            "environment": [
                {
                    "name": "TZ",
                    "value": "Asia/Seoul"
                }
            ],
            "essential": true,
            "image": "170454079061.dkr.ecr.ap-northeast-2.amazonaws.com/baromok/repo:ba90835c14bc66bf8df50a629499fe2120307b88",
            "memory": 358,
            "memoryReservation": 358,
            "mountPoints": [],
            "name": "baromok-container",
            "portMappings": [
                {
                    "appProtocol": "http",
                    "containerPort": 8080,
                    "hostPort": 0,
                    "name": "baromok-container-8080-tcp",
                    "protocol": "tcp"
                }
            ],
            "systemControls": [],
            "volumesFrom": []
        },
        {
            "cpu": 102,
            "environment": [
                {
                    "name": "TZ",
                    "value": "Asia/Seoul"
                }
            ],
            "environmentFiles": [],
            "essential": true,
            "image": "170454079061.dkr.ecr.ap-northeast-2.amazonaws.com/baromok/nginx",
            "memory": 102,
            "memoryReservation": 102,
            "mountPoints": [],
            "name": "nginx-container",
            "portMappings": [
                {
                    "appProtocol": "http",
                    "containerPort": 80,
                    "hostPort": 80,
                    "name": "nginx-container-80-tcp",
                    "protocol": "tcp"
                }
            ],
            "systemControls": [],
            "volumesFrom": [],
            "links": [
              "baromok-container"
            ]
        }
    ],
    "cpu": "1024",
    "executionRoleArn": "arn:aws:iam::170454079061:role/ecsTaskExecutionRole",
    "family": "baromok-task",
    "memory": "461",
    "networkMode": "bridge",
    "placementConstraints": [],
    "registeredAt": "2026-01-02T18:59:15.197Z",
    "registeredBy": "arn:aws:iam::170454079061:root",
    "requiresAttributes": [
        {
            "name": "com.amazonaws.ecs.capability.ecr-auth"
        },
        {
            "name": "com.amazonaws.ecs.capability.docker-remote-api.1.21"
        },
        {
            "name": "ecs.capability.execution-role-ecr-pull"
        }
    ],
    "requiresCompatibilities": [
        "EC2"
    ],
    "revision": 4,
    "runtimePlatform": {
        "cpuArchitecture": "X86_64",
        "operatingSystemFamily": "LINUX"
    },
    "status": "ACTIVE",
    "taskDefinitionArn": "arn:aws:ecs:ap-northeast-2:170454079061:task-definition/baromok-task:4",
    "volumes": [],
    "tags": []
}